inmanta_plugins/yum/__init__.py
inmanta_plugins/yum/setup.cfg
inmanta_plugins/yum/model/_init.cf
inmanta_plugins/yum/templates/repo.tmpl
inmanta_module_yum-2.1.1.dist-info/METADATA
inmanta_module_yum-2.1.1.dist-info/WHEEL
inmanta_module_yum-2.1.1.dist-info/top_level.txt
inmanta_module_yum-2.1.1.dist-info/RECORD
